{
  "id": "cyclops",
  "_index": 176,
  "name": "Cyclops",
  "abilityScores": {
    "STR": {
      "score": 22,
      "mod": 6,
      "ability": "STR"
    },
    "DEX": {
      "score": 11,
      "mod": 0,
      "ability": "DEX"
    },
    "CON": {
      "score": 20,
      "mod": 5,
      "ability": "CON"
    },
    "INT": {
      "score": 8,
      "mod": -1,
      "ability": "INT"
    },
    "WIS": {
      "score": 6,
      "mod": -2,
      "ability": "WIS"
    },
    "CHA": {
      "score": 10,
      "mod": 0,
      "ability": "CHA"
    }
  },
  "alignment": "CHAOTIC_NEUTRAL",
  "armorClass": "14 (natural armor)",
  "challengeRating": "6 (2,300 XP)",
  "hitPoints": {
    "average": 138,
    "roll": "12d12+60"
  },
  "race": "GIANT",
  "size": "Huge giant",
  "speed": "30 ft.",
  "senses": null,
  "source": "monster-manual",
  "languages": ["Giant"],
  "skills": [],
  "savingThrows": [],
  "abilities": [
    {
      "name": "Poor Depth Perception.",
      "description": "The cyclops has disadvantage on any attack roll against a target more than 30 ft. away.",
      "recharge": null
    }
  ],
  "image": "https://raw.githubusercontent.com/theoperatore/dnd-monster-api/master/src/db/assets/cyclops.jpg"
}
