{
  "abilityScores": {
    "STR": {
      "score": 16,
      "mod": 3,
      "ability": "STR"
    },
    "DEX": {
      "score": 14,
      "mod": 2,
      "ability": "DEX"
    },
    "CON": {
      "score": 14,
      "mod": 2,
      "ability": "CON"
    },
    "INT": {
      "score": 2,
      "mod": -4,
      "ability": "INT"
    },
    "WIS": {
      "score": 12,
      "mod": 1,
      "ability": "WIS"
    },
    "CHA": {
      "score": 7,
      "mod": -2,
      "ability": "CHA"
    }
  },
  "alignment": "unaligned",
  "armorClass": "12",
  "challengeRating": "1",
  "hitPoints": {
    "average": 45,
    "roll": "6d10+12"
  },
  "race": "beast",
  "size": "large",
  "speed": "50 ft.",
  "source": "monster-manual",
  "id": "giant_hyena",
  "name": "Giant Hyena",
  "_tags": [
    "large",
    "beast",
    "cr1",
    "monster-manual"
  ]
}
