{
  "abilityScores": {
    "STR": {
      "score": 18,
      "mod": 4,
      "ability": "STR"
    },
    "DEX": {
      "score": 16,
      "mod": 3,
      "ability": "DEX"
    },
    "CON": {
      "score": 16,
      "mod": 3,
      "ability": "CON"
    },
    "INT": {
      "score": 5,
      "mod": -3,
      "ability": "INT"
    },
    "WIS": {
      "score": 12,
      "mod": 1,
      "ability": "WIS"
    },
    "CHA": {
      "score": 7,
      "mod": -2,
      "ability": "CHA"
    }
  },
  "alignment": "unaligned",
  "armorClass": "13",
  "challengeRating": "4",
  "hitPoints": {
    "average": 59,
    "roll": "7d10+21"
  },
  "race": "monstrosity",
  "size": "large",
  "speed": "40 ft., climb 40 ft.",
  "source": "volos-guide",
  "id": "girallon",
  "name": "Girallon",
  "_tags": [
    "large",
    "monstrosity",
    "cr4",
    "volos-guide"
  ]
}
