{
  "abilityScores": {
    "STR": {
      "score": 19,
      "mod": 4,
      "ability": "STR"
    },
    "DEX": {
      "score": 10,
      "mod": 0,
      "ability": "DEX"
    },
    "CON": {
      "score": 17,
      "mod": 3,
      "ability": "CON"
    },
    "INT": {
      "score": 12,
      "mod": 1,
      "ability": "INT"
    },
    "WIS": {
      "score": 11,
      "mod": 0,
      "ability": "WIS"
    },
    "CHA": {
      "score": 15,
      "mod": 2,
      "ability": "CHA"
    }
  },
  "alignment": "chaotic good",
  "armorClass": "17 (natural armor)",
  "challengeRating": "6",
  "hitPoints": {
    "average": 110,
    "roll": "13d10+39"
  },
  "race": "dragon",
  "size": "large",
  "speed": "40 ft., burrow 20 ft., fly 80 ft.",
  "source": "monster-manual",
  "id": "young_brass_dragon",
  "name": "Young Brass Dragon",
  "_tags": [
    "large",
    "dragon",
    "cr6",
    "monster-manual"
  ]
}
